Flask_GeoIP-0.1.3.dist-info/DESCRIPTION.rst
Flask_GeoIP-0.1.3.dist-info/METADATA
Flask_GeoIP-0.1.3.dist-info/RECORD
Flask_GeoIP-0.1.3.dist-info/WHEEL
Flask_GeoIP-0.1.3.dist-info/entry_points.txt
Flask_GeoIP-0.1.3.dist-info/metadata.json
Flask_GeoIP-0.1.3.dist-info/pbr.json
Flask_GeoIP-0.1.3.dist-info/top_level.txt
flask_geoip/__init__.py
flask_geoip/metadata.py
flask_geoip/tests.py
