Metadata-Version: 2.0
Name: Flask-GeoIP
Version: 0.1.3
Summary: 
Requires-Dist: Flask (>=0.10.1)
Requires-Dist: pygeoip (>=0.2.7)
